llmops_observability/__init__.py
llmops_observability/asgi_middleware.py
llmops_observability/bedrock_instrumentation.py
llmops_observability/config.py
llmops_observability/llm.py
llmops_observability/sqs.py
llmops_observability/trace_manager.py
llmops_observability-20.0.0.dist-info/METADATA
llmops_observability-20.0.0.dist-info/WHEEL
llmops_observability-20.0.0.dist-info/top_level.txt
llmops_observability-20.0.0.dist-info/RECORD
