Metadata-Version: 2.4
Name: llmops-observability
Version: 20.0.0
Summary: LLMOps Observability SDK: decorators + SQS dispatch with compression
Requires-Python: >=3.9
Requires-Dist: python-dotenv
Requires-Dist: boto3
